flowpricer-0.1.0.dist-info/METADATA
flowpricer-0.1.0.dist-info/WHEEL
flowpricer-0.1.0.dist-info/license_files/LICENSE
flowpricer/__init__.py
flowpricer/flowpricer.cp312-win_amd64.pyd
flowpricer-0.1.0.dist-info/RECORD
